{
  "cardNo": "LO-0483",
  "title": "貧者の見識",
  "subName": "ランサー／カルナ",
  "name": "貧者の見識 ランサー／カルナ",
  "rawTypeJa": "キャラクター",
  "rawTypeKr": "캐릭터",
  "type": "character",
  "rarity": "C",
  "attributes": [
    "moon"
  ],
  "useTarget": [
    "moon",
    "moon",
    "moon",
    "moon"
  ],
  "ap": 3,
  "dp": 4,
  "sp": 2,
  "dmg": 2,
  "ex": 2,
  "costRaw": "月月月月",
  "restrictionRaw": "",
  "typeTagsRaw": "サーヴァント",
  "text": "[オーダーチェンジ:[0]]",
  "textKr": "[オーダーチェンジ:[0]]",
  "sourceUrl": "https://lycee-tcg.com/card/card_detail.pl?cardno=LO-0483"
}
