{
  "cardNo": "LO-0121",
  "title": "デジャヴワールド",
  "subName": "デジャヴ",
  "name": "デジャヴワールド デジャヴ",
  "rawTypeJa": "キャラクター",
  "rawTypeKr": "캐릭터",
  "type": "character",
  "rarity": "SR",
  "attributes": [
    "snow"
  ],
  "useTarget": [
    "snow",
    "snow"
  ],
  "ap": 1,
  "dp": 0,
  "sp": 0,
  "dmg": 3,
  "ex": 1,
  "costRaw": "雪雪",
  "restrictionRaw": "",
  "typeTagsRaw": "魔剣",
  "text": "[エンゲージ]\n[宣言] [雪雪雪雪]:このキャラの攻撃中に使用する。対戦キャラを破棄する。",
  "textKr": "[エンゲージ]\n[宣言] [雪雪雪雪]:このキャラの攻撃中に使用する。対戦キャラを破棄する。",
  "sourceUrl": "https://lycee-tcg.com/card/card_detail.pl?cardno=LO-0121"
}
