{
  "cardNo": "LO-0393",
  "title": "サンダース大学付属高校",
  "subName": "ケイ",
  "name": "サンダース大学付属高校 ケイ",
  "rawTypeJa": "キャラクター",
  "rawTypeKr": "캐릭터",
  "type": "character",
  "rarity": "R",
  "attributes": [
    "sun"
  ],
  "useTarget": [
    "moon",
    "cosmos",
    "sun"
  ],
  "ap": 6,
  "dp": 3,
  "sp": 2,
  "dmg": 3,
  "ex": 1,
  "costRaw": "月宙日",
  "restrictionRaw": "",
  "typeTagsRaw": "サンダース",
  "text": "[宣言] [無無]: {味方＜サンダース＞キャラ１体}にＡＰ＋１・ＤＰ＋１する。",
  "textKr": "[宣言] [無無]: {味方＜サンダース＞キャラ１体}にＡＰ＋１・ＤＰ＋１する。",
  "sourceUrl": "https://lycee-tcg.com/card/card_detail.pl?cardno=LO-0393",
  "parsedEffectsDraft": [
    {
      "header": "宣言",
      "timing": "onUse",
      "originalLine": "[宣言] [無無]: {味方<サンダース>キャラ1体}にAP+1・DP+1する。",
      "actions": [
        {
          "type": "modifyStat",
          "stat": "ap",
          "amount": 1
        }
      ]
    }
  ],
  "parseMeta": {
    "originalText": "[宣言] [無無]: {味方＜サンダース＞キャラ１体}にＡＰ＋１・ＤＰ＋１する。",
    "normalizedText": "[宣言] [無無]: {味方<サンダース>キャラ1体}にAP+1・DP+1する。",
    "lines": [
      "[宣言] [無無]: {味方<サンダース>キャラ1体}にAP+1・DP+1する。"
    ],
    "matchedRuleIds": [
      "modifyStat"
    ]
  },
  "unresolvedTextLines": []
}
