{
  "cardNo": "LO-1152",
  "title": "羽つき",
  "subName": "ユースティア・アストレア",
  "name": "羽つき ユースティア・アストレア",
  "rawTypeJa": "キャラクター",
  "rawTypeKr": "캐릭터",
  "type": "character",
  "rarity": "P",
  "attributes": [
    "flower"
  ],
  "useTarget": [
    "flower",
    "flower"
  ],
  "ap": 1,
  "dp": 3,
  "sp": 1,
  "dmg": 0,
  "ex": 2,
  "costRaw": "花花",
  "restrictionRaw": "",
  "typeTagsRaw": "",
  "text": "[宣言] [0]:{このキャラと同列の味方キャラ１体}にＳＰ＋１する。",
  "textKr": "[宣言] [0]:{このキャラと同列の味方キャラ１体}にＳＰ＋１する。",
  "sourceUrl": "https://lycee-tcg.com/card/card_detail.pl?cardno=LO-1152"
}
