{
  "cardNo": "LO-1211",
  "title": "悲しい思い出",
  "subName": "美坂 香里",
  "name": "悲しい思い出 美坂 香里",
  "rawTypeJa": "キャラクター",
  "rawTypeKr": "캐릭터",
  "type": "character",
  "rarity": "C",
  "attributes": [
    "moon"
  ],
  "useTarget": [
    "moon",
    "moon"
  ],
  "ap": 3,
  "dp": 1,
  "sp": 1,
  "dmg": 1,
  "ex": 2,
  "costRaw": "月月",
  "restrictionRaw": "",
  "typeTagsRaw": "",
  "text": "[宣言] [このキャラを破棄する]:{相手キャラ１体}にＤＭＧ－２する。",
  "textKr": "[宣言] [このキャラを破棄する]:{相手キャラ１体}にＤＭＧ－２する。",
  "sourceUrl": "https://lycee-tcg.com/card/card_detail.pl?cardno=LO-1211",
  "parsedEffectsDraft": [],
  "parseMeta": {
    "originalText": "[宣言] [このキャラを破棄する]:{相手キャラ１体}にＤＭＧ－２する。",
    "normalizedText": "[宣言] [このキャラを破棄する]:{相手キャラ1体}にDMG-2する。",
    "lines": [
      "[宣言] [このキャラを破棄する]:{相手キャラ1体}にDMG-2する。"
    ],
    "matchedRuleIds": []
  },
  "unresolvedTextLines": [
    {
      "line": "[宣言] [このキャラを破棄する]:{相手キャラ1体}にDMG-2する。",
      "reason": "no parser rule matched"
    }
  ]
}
