{
  "cardNo": "LO-2313",
  "title": "要石",
  "subName": "",
  "name": "要石",
  "rawTypeJa": "イベント",
  "rawTypeKr": "이벤트",
  "type": "event",
  "rarity": "U",
  "attributes": [
    "snow"
  ],
  "useTarget": [
    "snow",
    "snow",
    "snow"
  ],
  "ap": null,
  "dp": null,
  "sp": null,
  "dmg": null,
  "ex": 2,
  "costRaw": "雪雪雪",
  "restrictionRaw": "",
  "typeTagsRaw": "",
  "text": "バトル中に使用できない。{コストが２点以下の相手キャラ１体}を破棄する。相手のデッキを２枚破棄する。\n構築制限:[OSP]",
  "textKr": "バトル中に使用できない。{コストが２点以下の相手キャラ１体}を破棄する。相手のデッキを２枚破棄する。\n構築制限:[OSP]",
  "sourceUrl": "https://lycee-tcg.com/card/card_detail.pl?cardno=LO-2313",
  "parsedEffectsDraft": [],
  "parseMeta": {
    "originalText": "バトル中に使用できない。{コストが２点以下の相手キャラ１体}を破棄する。相手のデッキを２枚破棄する。\n構築制限:[OSP]",
    "normalizedText": "バトル中に使用できない。{コストが2点以下の相手キャラ1体}を破棄する。相手のデッキを2枚破棄する。\n構築制限:[OSP]",
    "lines": [
      "バトル中に使用できない。{コストが2点以下の相手キャラ1体}を破棄する。相手のデッキを2枚破棄する。",
      "構築制限:[OSP]"
    ],
    "matchedRuleIds": []
  },
  "unresolvedTextLines": [
    {
      "line": "バトル中に使用できない。{コストが2点以下の相手キャラ1体}を破棄する。相手のデッキを2枚破棄する。",
      "reason": "no parser rule matched"
    },
    {
      "line": "構築制限:[OSP]",
      "reason": "no parser rule matched"
    }
  ]
}
