{
  "cardNo": "LO-2388",
  "title": "皇帝",
  "subName": "霊帝・空丹",
  "name": "皇帝 霊帝・空丹",
  "rawTypeJa": "キャラクター",
  "rawTypeKr": "캐릭터",
  "type": "character",
  "rarity": "R",
  "attributes": [
    "flower"
  ],
  "useTarget": [
    "flower",
    "flower",
    "flower"
  ],
  "ap": 1,
  "dp": 4,
  "sp": 2,
  "dmg": 0,
  "ex": 2,
  "costRaw": "花花花",
  "restrictionRaw": "",
  "typeTagsRaw": "",
  "text": "[サポーター:[花]]\n[宣言] [花]:{自分のゴミ箱の[花]キャラ１体}を手札に入れる。この能力は失われる。\n[宣言] [花花花]:{味方[花]キャラ１体}を未行動にする。\n構築制限:[NEX]",
  "textKr": "[サポーター:[花]]\n[宣言] [花]:{自分のゴミ箱の[花]キャラ１体}を手札に入れる。この能力は失われる。\n[宣言] [花花花]:{味方[花]キャラ１体}を未行動にする。\n構築制限:[NEX]",
  "sourceUrl": "https://lycee-tcg.com/card/card_detail.pl?cardno=LO-2388",
  "parsedEffectsDraft": [
    {
      "header": "宣言",
      "timing": "onUse",
      "originalLine": "[宣言] [花]:{自分のゴミ箱の[花]キャラ1体}を手札に入れる。この能力は失われる。[宣言] [花花花]:{味方[花]キャラ1体}を未行動にする。構築制限:[NEX]",
      "actions": [
        {
          "type": "moveCard",
          "owner": "self",
          "from": "trash",
          "to": "hand",
          "count": 1
        }
      ]
    }
  ],
  "parseMeta": {
    "originalText": "[サポーター:[花]]\n[宣言] [花]:{自分のゴミ箱の[花]キャラ１体}を手札に入れる。この能力は失われる。\n[宣言] [花花花]:{味方[花]キャラ１体}を未行動にする。\n構築制限:[NEX]",
    "normalizedText": "[サポーター:[花]]\n[宣言] [花]:{自分のゴミ箱の[花]キャラ1体}を手札に入れる。この能力は失われる。[宣言] [花花花]:{味方[花]キャラ1体}を未行動にする。構築制限:[NEX]",
    "lines": [
      "[サポーター:[花]]",
      "[宣言] [花]:{自分のゴミ箱の[花]キャラ1体}を手札に入れる。この能力は失われる。[宣言] [花花花]:{味方[花]キャラ1体}を未行動にする。構築制限:[NEX]"
    ],
    "matchedRuleIds": [
      "moveCard:toHand"
    ]
  },
  "unresolvedTextLines": [
    {
      "line": "[サポーター:[花]]",
      "reason": "no parser rule matched"
    }
  ]
}
