{
  "cardNo": "LO-2449",
  "title": "南海覇王",
  "subName": "",
  "name": "南海覇王",
  "rawTypeJa": "アイテム",
  "rawTypeKr": "아이템",
  "type": "item",
  "rarity": "C",
  "attributes": [
    "moon"
  ],
  "useTarget": [
    "moon",
    "moon",
    "moon"
  ],
  "ap": null,
  "dp": null,
  "sp": null,
  "dmg": null,
  "ex": 2,
  "costRaw": "月月月",
  "restrictionRaw": "",
  "typeTagsRaw": "",
  "text": "装備制限:カード名に「孫」を含む＜呉＞キャラ\n[常時] このキャラにＡＰ＋１・ＤＰ＋１・ＤＭＧ＋１する。このキャラは[ボーナス:[相手のデッキを１枚破棄する。]]を得る。\n[誘発] このキャラが場を離れたとき、ゴミ箱のこのアイテムを味方キャラ１体に無償で装備する。\n※「南海覇王」は自分の場に１枚まで配置可能\n構築制限:[NEX]",
  "textKr": "装備制限:カード名に「孫」を含む＜呉＞キャラ\n[常時] このキャラにＡＰ＋１・ＤＰ＋１・ＤＭＧ＋１する。このキャラは[ボーナス:[相手のデッキを１枚破棄する。]]を得る。\n[誘発] このキャラが場を離れたとき、ゴミ箱のこのアイテムを味方キャラ１体に無償で装備する。\n※「南海覇王」は自分の場に１枚まで配置可能\n構築制限:[NEX]",
  "sourceUrl": "https://lycee-tcg.com/card/card_detail.pl?cardno=LO-2449",
  "parsedEffectsDraft": [
    {
      "header": "常時",
      "timing": "continuous",
      "originalLine": "[常時] このキャラにAP+1・DP+1・DMG+1する。このキャラは[ボーナス:[相手のデッキを1枚破棄する。]]を得る。",
      "actions": [
        {
          "type": "modifyStat",
          "stat": "ap",
          "amount": 1
        }
      ]
    }
  ],
  "parseMeta": {
    "originalText": "装備制限:カード名に「孫」を含む＜呉＞キャラ\n[常時] このキャラにＡＰ＋１・ＤＰ＋１・ＤＭＧ＋１する。このキャラは[ボーナス:[相手のデッキを１枚破棄する。]]を得る。\n[誘発] このキャラが場を離れたとき、ゴミ箱のこのアイテムを味方キャラ１体に無償で装備する。\n※「南海覇王」は自分の場に１枚まで配置可能\n構築制限:[NEX]",
    "normalizedText": "装備制限:カード名に「孫」を含む<呉>キャラ\n[常時] このキャラにAP+1・DP+1・DMG+1する。このキャラは[ボーナス:[相手のデッキを1枚破棄する。]]を得る。\n[誘発] このキャラが場を離れたとき、ゴミ箱のこのアイテムを味方キャラ1体に無償で装備する。\n※「南海覇王」は自分の場に1枚まで配置可能\n構築制限:[NEX]",
    "lines": [
      "装備制限:カード名に「孫」を含む<呉>キャラ",
      "[常時] このキャラにAP+1・DP+1・DMG+1する。このキャラは[ボーナス:[相手のデッキを1枚破棄する。]]を得る。",
      "[誘発] このキャラが場を離れたとき、ゴミ箱のこのアイテムを味方キャラ1体に無償で装備する。",
      "※「南海覇王」は自分の場に1枚まで配置可能",
      "構築制限:[NEX]"
    ],
    "matchedRuleIds": [
      "modifyStat"
    ]
  },
  "unresolvedTextLines": [
    {
      "line": "装備制限:カード名に「孫」を含む<呉>キャラ",
      "reason": "no parser rule matched"
    },
    {
      "line": "[誘発] このキャラが場を離れたとき、ゴミ箱のこのアイテムを味方キャラ1体に無償で装備する。",
      "reason": "no parser rule matched"
    },
    {
      "line": "※「南海覇王」は自分の場に1枚まで配置可能",
      "reason": "no parser rule matched"
    },
    {
      "line": "構築制限:[NEX]",
      "reason": "no parser rule matched"
    }
  ]
}
