{
  "cardNo": "LO-2850",
  "title": "神への復讐",
  "subName": "",
  "name": "神への復讐",
  "rawTypeJa": "エリア",
  "rawTypeKr": "에리어",
  "type": "area",
  "rarity": "U",
  "attributes": [
    "sun"
  ],
  "useTarget": [
    "sun",
    "sun"
  ],
  "ap": null,
  "dp": null,
  "sp": null,
  "dmg": null,
  "ex": 2,
  "costRaw": "日日",
  "restrictionRaw": "",
  "typeTagsRaw": "死んだ世界戦線",
  "text": "[宣言] [無]:{味方キャラ１体}にＡＰ＋３・ＤＰ－３する。この効果は失われる。\n[宣言] [D1]:相手ターン中に使用する。このエリアを破棄する。破棄したとき、{味方キャラ１体}にＡＰ＋４・ＤＰ－４する。\n※「神への復讐」は自分の場に１枚まで配置可能",
  "textKr": "[宣言] [無]:{味方キャラ１体}にＡＰ＋３・ＤＰ－３する。この効果は失われる。\n[宣言] [D1]:相手ターン中に使用する。このエリアを破棄する。破棄したとき、{味方キャラ１体}にＡＰ＋４・ＤＰ－４する。\n※「神への復讐」は自分の場に１枚まで配置可能",
  "sourceUrl": "https://lycee-tcg.com/card/card_detail.pl?cardno=LO-2850",
  "parsedEffectsDraft": [
    {
      "header": "宣言",
      "timing": "onUse",
      "originalLine": "[宣言] [無]:{味方キャラ1体}にAP+3・DP-3する。この効果は失われる。[宣言] [D1]:相手ターン中に使用する。このエリアを破棄する。破棄したとき、{味方キャラ1体}にAP+4・DP-4する。※「神への復讐」は自分の場に1枚まで配置可能",
      "actions": [
        {
          "type": "modifyStat",
          "stat": "ap",
          "amount": 3
        }
      ]
    }
  ],
  "parseMeta": {
    "originalText": "[宣言] [無]:{味方キャラ１体}にＡＰ＋３・ＤＰ－３する。この効果は失われる。\n[宣言] [D1]:相手ターン中に使用する。このエリアを破棄する。破棄したとき、{味方キャラ１体}にＡＰ＋４・ＤＰ－４する。\n※「神への復讐」は自分の場に１枚まで配置可能",
    "normalizedText": "[宣言] [無]:{味方キャラ1体}にAP+3・DP-3する。この効果は失われる。[宣言] [D1]:相手ターン中に使用する。このエリアを破棄する。破棄したとき、{味方キャラ1体}にAP+4・DP-4する。※「神への復讐」は自分の場に1枚まで配置可能",
    "lines": [
      "[宣言] [無]:{味方キャラ1体}にAP+3・DP-3する。この効果は失われる。[宣言] [D1]:相手ターン中に使用する。このエリアを破棄する。破棄したとき、{味方キャラ1体}にAP+4・DP-4する。※「神への復讐」は自分の場に1枚まで配置可能"
    ],
    "matchedRuleIds": [
      "modifyStat"
    ]
  },
  "unresolvedTextLines": []
}
