{
  "cardNo": "LO-3847",
  "title": "天下布武",
  "subName": "織田 久遠 信長",
  "name": "天下布武 織田 久遠 信長",
  "rawTypeJa": "キャラクター",
  "rawTypeKr": "캐릭터",
  "type": "character",
  "rarity": "SR",
  "attributes": [
    "cosmos"
  ],
  "useTarget": [
    "cosmos",
    "cosmos",
    "cosmos",
    "cosmos"
  ],
  "ap": 4,
  "dp": 4,
  "sp": 1,
  "dmg": 4,
  "ex": 2,
  "costRaw": "宙宙宙宙",
  "restrictionRaw": "－●－－●－",
  "typeTagsRaw": "",
  "text": "[オーダーステップ:[0]]\n[誘発] 相手ターン開始時、味方ＡＦキャラ全てがコストが３～４点で元の基本能力に[オーダーステップ]を持つ場合、味方キャラ１体を未行動にする。そのキャラをそのキャラと同列の味方ＤＦに移動できる。\n[誘発] 相手ターン開始時、自分の手札が３枚以上の場合、自分のゴミ箱の手札宣言能力を持つキャラ２体を自分の「天下布武」置き場に置ける。置いたとき、１枚ドローする。ターン終了時まで、次に自分の元の能力でドローしたとき、自分の手札を１枚破棄する。\n[手札宣言] [宙宙]:{コストが３～４点の味方キャラ１体}にＡＰ＋２・ＤＰ＋２する。自ターン中の場合、１枚ドローする。",
  "textKr": "[オーダーステップ:[0]]\n[誘発] 相手ターン開始時、味方ＡＦキャラ全てがコストが３～４点で元の基本能力に[オーダーステップ]を持つ場合、味方キャラ１体を未行動にする。そのキャラをそのキャラと同列の味方ＤＦに移動できる。\n[誘発] 相手ターン開始時、自分の手札が３枚以上の場合、自分のゴミ箱の手札宣言能力を持つキャラ２体を自分の「天下布武」置き場に置ける。置いたとき、１枚ドローする。ターン終了時まで、次に自分の元の能力でドローしたとき、自分の手札を１枚破棄する。\n[手札宣言] [宙宙]:{コストが３～４点の味方キャラ１体}にＡＰ＋２・ＤＰ＋２する。自ターン中の場合、１枚ドローする。",
  "sourceUrl": "https://lycee-tcg.com/card/card_detail.pl?cardno=LO-3847"
}
