{
  "cardNo": "LO-3501",
  "title": "Dusk Bringer Sower of Huge",
  "subName": "不二",
  "name": "Dusk Bringer Sower of Huge 不二",
  "rawTypeJa": "キャラクター",
  "rawTypeKr": "캐릭터",
  "type": "character",
  "rarity": "C",
  "attributes": [
    "cosmos"
  ],
  "useTarget": [
    "cosmos",
    "cosmos",
    "cosmos",
    "cosmos",
    "cosmos"
  ],
  "ap": 5,
  "dp": 5,
  "sp": 1,
  "dmg": 5,
  "ex": 2,
  "costRaw": "宙宙宙宙宙",
  "restrictionRaw": "",
  "typeTagsRaw": "",
  "text": "[ステップ:[0]]\n[誘発] コストが５点以上の味方キャラを相手の効果で破棄したとき、１枚ドローできる。\n[宣言] [0]:自ターン中に使用する。バトル中に使用できない。未行動のこのキャラと味方「エリス」１体を入れ替える。",
  "textKr": "[ステップ:[0]]\n[誘発] コストが５点以上の味方キャラを相手の効果で破棄したとき、１枚ドローできる。\n[宣言] [0]:自ターン中に使用する。バトル中に使用できない。未行動のこのキャラと味方「エリス」１体を入れ替える。",
  "sourceUrl": "https://lycee-tcg.com/card/card_detail.pl?cardno=LO-3501",
  "parsedEffectsDraft": [
    {
      "header": "誘発",
      "timing": "unknown",
      "originalLine": "[誘発] コストが5点以上の味方キャラを相手の効果で破棄したとき、1枚ドローできる。[宣言] [0]:自ターン中に使用する。バトル中に使用できない。未行動のこのキャラと味方「エリス」1体を入れ替える。",
      "actions": [
        {
          "type": "draw",
          "amount": 1
        }
      ]
    }
  ],
  "parseMeta": {
    "originalText": "[ステップ:[0]]\n[誘発] コストが５点以上の味方キャラを相手の効果で破棄したとき、１枚ドローできる。\n[宣言] [0]:自ターン中に使用する。バトル中に使用できない。未行動のこのキャラと味方「エリス」１体を入れ替える。",
    "normalizedText": "[ステップ:[0]]\n[誘発] コストが5点以上の味方キャラを相手の効果で破棄したとき、1枚ドローできる。[宣言] [0]:自ターン中に使用する。バトル中に使用できない。未行動のこのキャラと味方「エリス」1体を入れ替える。",
    "lines": [
      "[ステップ:[0]]",
      "[誘発] コストが5点以上の味方キャラを相手の効果で破棄したとき、1枚ドローできる。[宣言] [0]:自ターン中に使用する。バトル中に使用できない。未行動のこのキャラと味方「エリス」1体を入れ替える。"
    ],
    "matchedRuleIds": [
      "draw"
    ]
  },
  "unresolvedTextLines": [
    {
      "line": "[ステップ:[0]]",
      "reason": "no parser rule matched"
    }
  ]
}
