{
  "cardNo": "LO-3524",
  "title": "人機",
  "subName": "",
  "name": "人機",
  "rawTypeJa": "アイテム",
  "rawTypeKr": "아이템",
  "type": "item",
  "rarity": "R",
  "attributes": [
    "moon"
  ],
  "useTarget": [
    "moon",
    "moon",
    "moon"
  ],
  "ap": null,
  "dp": null,
  "sp": null,
  "dmg": null,
  "ex": 2,
  "costRaw": "月月月",
  "restrictionRaw": "",
  "typeTagsRaw": "",
  "text": "[常時] このキャラにＡＰ＋２・ＤＰ＋２する。\n[誘発] 相手ターン開始時、味方キャラ全てがコストが５点以上で、味方ＤＦキャラが１体以下の場合、相手キャラ１体にＤＭＧ－１する。\n[宣言] [月月月]:自ターン中に使用する。バトル中に使用できない。自分の手札のコストが[月]または[無]のみで６点以下のキャラ１体を無償で登場する。味方キャラが２体以下の場合、１枚ドローする。（１回まで使用可能）",
  "textKr": "[常時] このキャラにＡＰ＋２・ＤＰ＋２する。\n[誘発] 相手ターン開始時、味方キャラ全てがコストが５点以上で、味方ＤＦキャラが１体以下の場合、相手キャラ１体にＤＭＧ－１する。\n[宣言] [月月月]:自ターン中に使用する。バトル中に使用できない。自分の手札のコストが[月]または[無]のみで６点以下のキャラ１体を無償で登場する。味方キャラが２体以下の場合、１枚ドローする。（１回まで使用可能）",
  "sourceUrl": "https://lycee-tcg.com/card/card_detail.pl?cardno=LO-3524",
  "parsedEffectsDraft": [
    {
      "header": "常時",
      "timing": "continuous",
      "originalLine": "[常時] このキャラにAP+2・DP+2する。",
      "actions": [
        {
          "type": "modifyStat",
          "stat": "ap",
          "amount": 2
        }
      ]
    },
    {
      "header": "宣言",
      "timing": "onUse",
      "originalLine": "[宣言] [月月月]:自ターン中に使用する。バトル中に使用できない。自分の手札のコストが[月]または[無]のみで6点以下のキャラ1体を無償で登場する。味方キャラが2体以下の場合、1枚ドローする。(1回まで使用可能)",
      "actions": [
        {
          "type": "draw",
          "amount": 1
        }
      ]
    }
  ],
  "parseMeta": {
    "originalText": "[常時] このキャラにＡＰ＋２・ＤＰ＋２する。\n[誘発] 相手ターン開始時、味方キャラ全てがコストが５点以上で、味方ＤＦキャラが１体以下の場合、相手キャラ１体にＤＭＧ－１する。\n[宣言] [月月月]:自ターン中に使用する。バトル中に使用できない。自分の手札のコストが[月]または[無]のみで６点以下のキャラ１体を無償で登場する。味方キャラが２体以下の場合、１枚ドローする。（１回まで使用可能）",
    "normalizedText": "[常時] このキャラにAP+2・DP+2する。\n[誘発] 相手ターン開始時、味方キャラ全てがコストが5点以上で、味方DFキャラが1体以下の場合、相手キャラ1体にDMG-1する。\n[宣言] [月月月]:自ターン中に使用する。バトル中に使用できない。自分の手札のコストが[月]または[無]のみで6点以下のキャラ1体を無償で登場する。味方キャラが2体以下の場合、1枚ドローする。(1回まで使用可能)",
    "lines": [
      "[常時] このキャラにAP+2・DP+2する。",
      "[誘発] 相手ターン開始時、味方キャラ全てがコストが5点以上で、味方DFキャラが1体以下の場合、相手キャラ1体にDMG-1する。",
      "[宣言] [月月月]:自ターン中に使用する。バトル中に使用できない。自分の手札のコストが[月]または[無]のみで6点以下のキャラ1体を無償で登場する。味方キャラが2体以下の場合、1枚ドローする。(1回まで使用可能)"
    ],
    "matchedRuleIds": [
      "modifyStat",
      "draw"
    ]
  },
  "unresolvedTextLines": [
    {
      "line": "[誘発] 相手ターン開始時、味方キャラ全てがコストが5点以上で、味方DFキャラが1体以下の場合、相手キャラ1体にDMG-1する。",
      "reason": "no parser rule matched"
    }
  ]
}
