{
  "cardNo": "LO-3790",
  "title": "竜姫",
  "subName": "メリュジアナ",
  "name": "竜姫 メリュジアナ",
  "rawTypeJa": "キャラクター",
  "rawTypeKr": "캐릭터",
  "type": "character",
  "rarity": "U",
  "attributes": [
    "sun"
  ],
  "useTarget": [
    "sun",
    "sun",
    "sun",
    "sun",
    "sun",
    "sun"
  ],
  "ap": 5,
  "dp": 5,
  "sp": 1,
  "dmg": 5,
  "ex": 2,
  "costRaw": "日日日日日日",
  "restrictionRaw": "",
  "typeTagsRaw": "",
  "text": "[ジャンプ:[0]]\n[宣言] [0]:{コストが２点以下の味方[日]キャラ１体}にＡＰ＋２する。\n[誘発] このキャラが相手の効果で場を離れたとき、２枚ドローできる。自分のデッキを２枚回復しシャッフルする。\n構築制限:[AIG]",
  "textKr": "[ジャンプ:[0]]\n[宣言] [0]:{コストが２点以下の味方[日]キャラ１体}にＡＰ＋２する。\n[誘発] このキャラが相手の効果で場を離れたとき、２枚ドローできる。自分のデッキを２枚回復しシャッフルする。\n構築制限:[AIG]",
  "sourceUrl": "https://lycee-tcg.com/card/card_detail.pl?cardno=LO-3790",
  "parsedEffectsDraft": [
    {
      "header": "宣言",
      "timing": "onUse",
      "originalLine": "[宣言] [0]:{コストが2点以下の味方[日]キャラ1体}にAP+2する。",
      "actions": [
        {
          "type": "modifyStat",
          "stat": "ap",
          "amount": 2
        }
      ]
    },
    {
      "header": "誘発",
      "timing": "unknown",
      "originalLine": "[誘発] このキャラが相手の効果で場を離れたとき、2枚ドローできる。自分のデッキを2枚回復しシャッフルする。",
      "actions": [
        {
          "type": "draw",
          "amount": 2
        }
      ]
    }
  ],
  "parseMeta": {
    "originalText": "[ジャンプ:[0]]\n[宣言] [0]:{コストが２点以下の味方[日]キャラ１体}にＡＰ＋２する。\n[誘発] このキャラが相手の効果で場を離れたとき、２枚ドローできる。自分のデッキを２枚回復しシャッフルする。\n構築制限:[AIG]",
    "normalizedText": "[ジャンプ:[0]]\n[宣言] [0]:{コストが2点以下の味方[日]キャラ1体}にAP+2する。\n[誘発] このキャラが相手の効果で場を離れたとき、2枚ドローできる。自分のデッキを2枚回復しシャッフルする。\n構築制限:[AIG]",
    "lines": [
      "[ジャンプ:[0]]",
      "[宣言] [0]:{コストが2点以下の味方[日]キャラ1体}にAP+2する。",
      "[誘発] このキャラが相手の効果で場を離れたとき、2枚ドローできる。自分のデッキを2枚回復しシャッフルする。",
      "構築制限:[AIG]"
    ],
    "matchedRuleIds": [
      "modifyStat",
      "draw"
    ]
  },
  "unresolvedTextLines": [
    {
      "line": "[ジャンプ:[0]]",
      "reason": "no parser rule matched"
    },
    {
      "line": "構築制限:[AIG]",
      "reason": "no parser rule matched"
    }
  ]
}
