{
  "cardNo": "LO-4883",
  "title": "家庭的な吸血鬼",
  "subName": "稲叢 莉音",
  "name": "家庭的な吸血鬼 稲叢 莉音",
  "rawTypeJa": "キャラクター",
  "rawTypeKr": "캐릭터",
  "type": "character",
  "rarity": "C",
  "attributes": [
    "snow"
  ],
  "useTarget": [
    "snow",
    "snow",
    "star"
  ],
  "ap": 4,
  "dp": 4,
  "sp": 1,
  "dmg": 3,
  "ex": 2,
  "costRaw": "雪雪無",
  "restrictionRaw": "",
  "typeTagsRaw": "",
  "text": "[ボーナス:[自分のデッキを１枚回復できる。]]\n[誘発] 自分の効果で相手キャラが場を離れたとき、このキャラにＡＰ＋２・ＤＰ＋２・ＤＭＧ＋１する。",
  "textKr": "[ボーナス:[自分のデッキを１枚回復できる。]]\n[誘発] 自分の効果で相手キャラが場を離れたとき、このキャラにＡＰ＋２・ＤＰ＋２・ＤＭＧ＋１する。",
  "sourceUrl": "https://lycee-tcg.com/card/card_detail.pl?cardno=LO-4883"
}
