{
  "cardNo": "LO-4323",
  "title": "控えめで文系の女の子",
  "subName": "如月 のえ",
  "name": "控えめで文系の女の子 如月 のえ",
  "rawTypeJa": "キャラクター",
  "rawTypeKr": "캐릭터",
  "type": "character",
  "rarity": "U",
  "attributes": [
    "flower"
  ],
  "useTarget": [
    "flower",
    "flower",
    "flower"
  ],
  "ap": 0,
  "dp": 5,
  "sp": 2,
  "dmg": 0,
  "ex": 2,
  "costRaw": "花花花",
  "restrictionRaw": "－－－●●●",
  "typeTagsRaw": "",
  "text": "[サポーター:[花花]]\n[誘発] このキャラが登場したとき、味方[花]キャラ１体にＡＰ＋１・ＤＰ＋１・ＤＭＧ＋１する。コストが３点以上の味方[花]キャラが４体以上登場している場合、１枚ドローする。",
  "textKr": "[サポーター:[花花]]\n[誘発] このキャラが登場したとき、味方[花]キャラ１体にＡＰ＋１・ＤＰ＋１・ＤＭＧ＋１する。コストが３点以上の味方[花]キャラが４体以上登場している場合、１枚ドローする。",
  "sourceUrl": "https://lycee-tcg.com/card/card_detail.pl?cardno=LO-4323",
  "parsedEffectsDraft": [
    {
      "header": "誘発",
      "timing": "onEnter",
      "triggerText": "このキャラが登場したとき",
      "originalLine": "[誘発] このキャラが登場したとき、味方[花]キャラ1体にAP+1・DP+1・DMG+1する。コストが3点以上の味方[花]キャラが4体以上登場している場合、1枚ドローする。",
      "actions": [
        {
          "type": "draw",
          "amount": 1
        }
      ]
    }
  ],
  "parseMeta": {
    "originalText": "[サポーター:[花花]]\n[誘発] このキャラが登場したとき、味方[花]キャラ１体にＡＰ＋１・ＤＰ＋１・ＤＭＧ＋１する。コストが３点以上の味方[花]キャラが４体以上登場している場合、１枚ドローする。",
    "normalizedText": "[サポーター:[花花]]\n[誘発] このキャラが登場したとき、味方[花]キャラ1体にAP+1・DP+1・DMG+1する。コストが3点以上の味方[花]キャラが4体以上登場している場合、1枚ドローする。",
    "lines": [
      "[サポーター:[花花]]",
      "[誘発] このキャラが登場したとき、味方[花]キャラ1体にAP+1・DP+1・DMG+1する。コストが3点以上の味方[花]キャラが4体以上登場している場合、1枚ドローする。"
    ],
    "matchedRuleIds": [
      "draw"
    ]
  },
  "unresolvedTextLines": [
    {
      "line": "[サポーター:[花花]]",
      "reason": "no parser rule matched"
    }
  ]
}
