{
  "cardNo": "LO-4772",
  "title": "天地に荒ぶ紅蓮の咆哮",
  "subName": "シャロン",
  "name": "天地に荒ぶ紅蓮の咆哮 シャロン",
  "rawTypeJa": "キャラクター",
  "rawTypeKr": "캐릭터",
  "type": "character",
  "rarity": "R",
  "attributes": [
    "cosmos"
  ],
  "useTarget": [
    "cosmos",
    "cosmos",
    "cosmos"
  ],
  "ap": 5,
  "dp": 5,
  "sp": 0,
  "dmg": 4,
  "ex": 2,
  "costRaw": "宙宙宙",
  "restrictionRaw": "",
  "typeTagsRaw": "",
  "text": "[誘発] このキャラが手札から登場したとき、またはターン開始時、コストが３～４点の味方[宙]キャラ１体にＡＰ＋２またはＤＰ＋２する。\n[宣言] [宙]:自ターン中に使用する。バトル中に使用できない。味方[宙]キャラが６体以上登場している場合、このキャラを破棄する。破棄したとき、自分のゴミ箱または自分のデッキから「シャロン（ドラゴニア形態）」１体を探し無償で登場する。\n[手札宣言] [宙]:このターン中、相手の効果で登場が失敗したまたは手札から破棄した、自分のゴミ箱のコストが[宙]または[無]のみで４点以下の[宙]キャラ１体を無償で登場する。",
  "textKr": "[誘発] このキャラが手札から登場したとき、またはターン開始時、コストが３～４点の味方[宙]キャラ１体にＡＰ＋２またはＤＰ＋２する。\n[宣言] [宙]:自ターン中に使用する。バトル中に使用できない。味方[宙]キャラが６体以上登場している場合、このキャラを破棄する。破棄したとき、自分のゴミ箱または自分のデッキから「シャロン（ドラゴニア形態）」１体を探し無償で登場する。\n[手札宣言] [宙]:このターン中、相手の効果で登場が失敗したまたは手札から破棄した、自分のゴミ箱のコストが[宙]または[無]のみで４点以下の[宙]キャラ１体を無償で登場する。",
  "sourceUrl": "https://lycee-tcg.com/card/card_detail.pl?cardno=LO-4772"
}
