{
  "cardNo": "LO-4594",
  "title": "学園の才媛",
  "subName": "ミリーナ・リリアーノ",
  "name": "学園の才媛 ミリーナ・リリアーノ",
  "rawTypeJa": "キャラクター",
  "rawTypeKr": "캐릭터",
  "type": "character",
  "rarity": "R",
  "attributes": [
    "snow"
  ],
  "useTarget": [
    "snow",
    "snow",
    "snow"
  ],
  "ap": 4,
  "dp": 4,
  "sp": 2,
  "dmg": 3,
  "ex": 1,
  "costRaw": "雪雪雪",
  "restrictionRaw": "",
  "typeTagsRaw": "",
  "text": "[チャージ:１]\n[誘発] 自ターン中、自分のコストが１点以上のイベント・手札宣言能力を使用したとき、自分にシールド＋１する。未行動の味方[雪]キャラ１体に相手ターン終了時までＡＰ＋１・ＤＰ＋１する。このキャラのチャージ１枚を破棄できる。破棄したとき、１枚ドローする。\n[手札宣言] [雪雪雪]:自ターン中に使用する。バトル中に使用できない。{相手キャラ１体}を破棄する。",
  "textKr": "[チャージ:１]\n[誘発] 自ターン中、自分のコストが１点以上のイベント・手札宣言能力を使用したとき、自分にシールド＋１する。未行動の味方[雪]キャラ１体に相手ターン終了時までＡＰ＋１・ＤＰ＋１する。このキャラのチャージ１枚を破棄できる。破棄したとき、１枚ドローする。\n[手札宣言] [雪雪雪]:自ターン中に使用する。バトル中に使用できない。{相手キャラ１体}を破棄する。",
  "sourceUrl": "https://lycee-tcg.com/card/card_detail.pl?cardno=LO-4594",
  "parsedEffectsDraft": [
    {
      "header": "誘発",
      "timing": "onTurnEnd",
      "conditionText": "自ターン中",
      "conditions": [
        {
          "type": "turn",
          "side": "self"
        }
      ],
      "originalLine": "[誘発] 自ターン中、自分のコストが1点以上のイベント・手札宣言能力を使用したとき、自分にシールド+1する。未行動の味方[雪]キャラ1体に相手ターン終了時までAP+1・DP+1する。このキャラのチャージ1枚を破棄できる。破棄したとき、1枚ドローする。",
      "actions": [
        {
          "type": "modifyStat",
          "stat": "ap",
          "amount": 1,
          "duration": "endOfTurn"
        }
      ]
    }
  ],
  "parseMeta": {
    "originalText": "[チャージ:１]\n[誘発] 自ターン中、自分のコストが１点以上のイベント・手札宣言能力を使用したとき、自分にシールド＋１する。未行動の味方[雪]キャラ１体に相手ターン終了時までＡＰ＋１・ＤＰ＋１する。このキャラのチャージ１枚を破棄できる。破棄したとき、１枚ドローする。\n[手札宣言] [雪雪雪]:自ターン中に使用する。バトル中に使用できない。{相手キャラ１体}を破棄する。",
    "normalizedText": "[チャージ:1]\n[誘発] 自ターン中、自分のコストが1点以上のイベント・手札宣言能力を使用したとき、自分にシールド+1する。未行動の味方[雪]キャラ1体に相手ターン終了時までAP+1・DP+1する。このキャラのチャージ1枚を破棄できる。破棄したとき、1枚ドローする。\n[手札宣言] [雪雪雪]:自ターン中に使用する。バトル中に使用できない。{相手キャラ1体}を破棄する。",
    "lines": [
      "[チャージ:1]",
      "[誘発] 自ターン中、自分のコストが1点以上のイベント・手札宣言能力を使用したとき、自分にシールド+1する。未行動の味方[雪]キャラ1体に相手ターン終了時までAP+1・DP+1する。このキャラのチャージ1枚を破棄できる。破棄したとき、1枚ドローする。",
      "[手札宣言] [雪雪雪]:自ターン中に使用する。バトル中に使用できない。{相手キャラ1体}を破棄する。"
    ],
    "matchedRuleIds": [
      "modifyStat:endOfTurn"
    ]
  },
  "unresolvedTextLines": [
    {
      "line": "[チャージ:1]",
      "reason": "no parser rule matched"
    },
    {
      "line": "[手札宣言] [雪雪雪]:自ターン中に使用する。バトル中に使用できない。{相手キャラ1体}を破棄する。",
      "reason": "no parser rule matched"
    }
  ]
}
