{
  "cardNo": "LO-5191",
  "title": "熱砂の守人",
  "subName": "エルルゥ",
  "name": "熱砂の守人 エルルゥ",
  "rawTypeJa": "キャラクター",
  "rawTypeKr": "캐릭터",
  "type": "character",
  "rarity": "P",
  "attributes": [
    "cosmos"
  ],
  "useTarget": [
    "cosmos",
    "cosmos"
  ],
  "ap": 1,
  "dp": 3,
  "sp": 1,
  "dmg": 0,
  "ex": 2,
  "costRaw": "宙宙",
  "restrictionRaw": "－－－●●●",
  "typeTagsRaw": "",
  "text": "[誘発] このキャラが手札から登場したときまたはターン開始時、コストが３点以上または『うたわれるもの ロストフラグ』の味方[宙]キャラ１体にＡＰ＋１・ＤＰ＋１する。\n[宣言] [0]:{味方防御キャラ１体}にＤＰ＋２する。この能力は失われる。",
  "textKr": "[誘発] このキャラが手札から登場したときまたはターン開始時、コストが３点以上または『うたわれるもの ロストフラグ』の味方[宙]キャラ１体にＡＰ＋１・ＤＰ＋１する。\n[宣言] [0]:{味方防御キャラ１体}にＤＰ＋２する。この能力は失われる。",
  "sourceUrl": "https://lycee-tcg.com/card/card_detail.pl?cardno=LO-5191"
}
