{
  "cardNo": "LO-5337",
  "title": "ネイルもバッチリ！",
  "subName": "華野 椎名",
  "name": "ネイルもバッチリ！ 華野 椎名",
  "rawTypeJa": "キャラクター",
  "rawTypeKr": "캐릭터",
  "type": "character",
  "rarity": "P",
  "attributes": [
    "flower"
  ],
  "useTarget": [
    "flower",
    "flower",
    "star"
  ],
  "ap": 1,
  "dp": 4,
  "sp": 3,
  "dmg": 0,
  "ex": 2,
  "costRaw": "花花無",
  "restrictionRaw": "",
  "typeTagsRaw": "",
  "text": "[宣言] [0]:このキャラがアイテムを持つ場合、このキャラにＤＰ＋１・ＳＰ＋１する。",
  "textKr": "[宣言] [0]:このキャラがアイテムを持つ場合、このキャラにＤＰ＋１・ＳＰ＋１する。",
  "sourceUrl": "https://lycee-tcg.com/card/card_detail.pl?cardno=LO-5337",
  "parsedEffectsDraft": [
    {
      "header": "宣言",
      "timing": "onUse",
      "originalLine": "[宣言] [0]:このキャラがアイテムを持つ場合、このキャラにDP+1・SP+1する。",
      "actions": [
        {
          "type": "modifyStat",
          "stat": "dp",
          "amount": 1
        }
      ]
    }
  ],
  "parseMeta": {
    "originalText": "[宣言] [0]:このキャラがアイテムを持つ場合、このキャラにＤＰ＋１・ＳＰ＋１する。",
    "normalizedText": "[宣言] [0]:このキャラがアイテムを持つ場合、このキャラにDP+1・SP+1する。",
    "lines": [
      "[宣言] [0]:このキャラがアイテムを持つ場合、このキャラにDP+1・SP+1する。"
    ],
    "matchedRuleIds": [
      "modifyStat"
    ]
  },
  "unresolvedTextLines": []
}
