{
  "cardNo": "LO-5618",
  "title": "超絶人見知り",
  "subName": "高町 雪乃",
  "name": "超絶人見知り 高町 雪乃",
  "rawTypeJa": "キャラクター",
  "rawTypeKr": "캐릭터",
  "type": "character",
  "rarity": "U",
  "attributes": [
    "sun"
  ],
  "useTarget": [
    "sun",
    "sun"
  ],
  "ap": 2,
  "dp": 3,
  "sp": 2,
  "dmg": 0,
  "ex": 2,
  "costRaw": "日日",
  "restrictionRaw": "－－－●●●",
  "typeTagsRaw": "",
  "text": "[サイドステップ:[0]]\n[誘発] このキャラが登場したとき、１枚ドローする。\n[手札宣言] [0]:対応・バトル中を除く自ターン中に使用する。相手はこの宣言に対応して宣言できない。味方「半吸血鬼のアイドルの卵 ルーチュ・アストラム」１体を破棄する。破棄したとき、自分のゴミ箱または自分のデッキから「二代目チュチュ チューノ・チュラム」１体を探し無償で登場する。自分のゴミ箱のこのキャラと「ルーチュ・アストラム」１体をそのキャラにチャージとして置ける。\n構築制限:【[AMC]】【[日]】【禁止:コストが３～４点のキャラ】",
  "textKr": "[サイドステップ:[0]]\n[誘発] このキャラが登場したとき、１枚ドローする。\n[手札宣言] [0]:対応・バトル中を除く自ターン中に使用する。相手はこの宣言に対応して宣言できない。味方「半吸血鬼のアイドルの卵 ルーチュ・アストラム」１体を破棄する。破棄したとき、自分のゴミ箱または自分のデッキから「二代目チュチュ チューノ・チュラム」１体を探し無償で登場する。自分のゴミ箱のこのキャラと「ルーチュ・アストラム」１体をそのキャラにチャージとして置ける。\n構築制限:【[AMC]】【[日]】【禁止:コストが３～４点のキャラ】",
  "sourceUrl": "https://lycee-tcg.com/card/card_detail.pl?cardno=LO-5618",
  "parsedEffectsDraft": [
    {
      "header": "誘発",
      "timing": "onEnter",
      "triggerText": "このキャラが登場したとき",
      "originalLine": "[誘発] このキャラが登場したとき、1枚ドローする。",
      "actions": [
        {
          "type": "draw",
          "amount": 1
        }
      ]
    },
    {
      "header": "手札宣言",
      "timing": "onUse",
      "originalLine": "[手札宣言] [0]:対応・バトル中を除く自ターン中に使用する。相手はこの宣言に対応して宣言できない。味方「半吸血鬼のアイドルの卵 ルーチュ・アストラム」1体を破棄する。破棄したとき、自分のゴミ箱または自分のデッキから「二代目チュチュ チューノ・チュラム」1体を探し無償で登場する。自分のゴミ箱のこのキャラと「ルーチュ・アストラム」1体をそのキャラにチャージとして置ける。",
      "actions": [
        {
          "type": "searchCard",
          "owner": "opponent",
          "zones": [
            "deck",
            "trash"
          ],
          "match": {
            "exactName": "半吸血鬼のアイドルの卵 ルーチュ・アストラム",
            "kind": "event"
          },
          "min": 0,
          "max": 0,
          "storeAs": "lastSearchResult",
          "shuffleAfterSearch": true
        },
        {
          "type": "freeUse",
          "sourceRef": "lastSearchResult",
          "useKind": "event",
          "ignoreCost": true
        }
      ]
    }
  ],
  "parseMeta": {
    "originalText": "[サイドステップ:[0]]\n[誘発] このキャラが登場したとき、１枚ドローする。\n[手札宣言] [0]:対応・バトル中を除く自ターン中に使用する。相手はこの宣言に対応して宣言できない。味方「半吸血鬼のアイドルの卵 ルーチュ・アストラム」１体を破棄する。破棄したとき、自分のゴミ箱または自分のデッキから「二代目チュチュ チューノ・チュラム」１体を探し無償で登場する。自分のゴミ箱のこのキャラと「ルーチュ・アストラム」１体をそのキャラにチャージとして置ける。\n構築制限:【[AMC]】【[日]】【禁止:コストが３～４点のキャラ】",
    "normalizedText": "[サイドステップ:[0]]\n[誘発] このキャラが登場したとき、1枚ドローする。\n[手札宣言] [0]:対応・バトル中を除く自ターン中に使用する。相手はこの宣言に対応して宣言できない。味方「半吸血鬼のアイドルの卵 ルーチュ・アストラム」1体を破棄する。破棄したとき、自分のゴミ箱または自分のデッキから「二代目チュチュ チューノ・チュラム」1体を探し無償で登場する。自分のゴミ箱のこのキャラと「ルーチュ・アストラム」1体をそのキャラにチャージとして置ける。\n構築制限:【[AMC]】【[日]】【禁止:コストが3~4点のキャラ】",
    "lines": [
      "[サイドステップ:[0]]",
      "[誘発] このキャラが登場したとき、1枚ドローする。",
      "[手札宣言] [0]:対応・バトル中を除く自ターン中に使用する。相手はこの宣言に対応して宣言できない。味方「半吸血鬼のアイドルの卵 ルーチュ・アストラム」1体を破棄する。破棄したとき、自分のゴミ箱または自分のデッキから「二代目チュチュ チューノ・チュラム」1体を探し無償で登場する。自分のゴミ箱のこのキャラと「ルーチュ・アストラム」1体をそのキャラにチャージとして置ける。",
      "構築制限:【[AMC]】【[日]】【禁止:コストが3~4点のキャラ】"
    ],
    "matchedRuleIds": [
      "draw",
      "searchCard+freeUse"
    ]
  },
  "unresolvedTextLines": [
    {
      "line": "[サイドステップ:[0]]",
      "reason": "no parser rule matched"
    },
    {
      "line": "構築制限:【[AMC]】【[日]】【禁止:コストが3~4点のキャラ】",
      "reason": "no parser rule matched"
    }
  ]
}
