{
  "cardNo": "LO-5644",
  "title": "ハラペコブラザーズ",
  "subName": "稲羽 結衣",
  "name": "ハラペコブラザーズ 稲羽 結衣",
  "rawTypeJa": "キャラクター",
  "rawTypeKr": "캐릭터",
  "type": "character",
  "rarity": "P",
  "attributes": [
    "flower"
  ],
  "useTarget": [
    "flower",
    "flower",
    "flower"
  ],
  "ap": 0,
  "dp": 4,
  "sp": 2,
  "dmg": 0,
  "ex": 2,
  "costRaw": "花花花",
  "restrictionRaw": "－－－●●●",
  "typeTagsRaw": "",
  "text": "[サポーター:[花]]\n[誘発] このキャラが手札から登場したとき、コストが３点以上の味方[花]キャラが３体以上の場合、２枚ドローする。自分にシールド＋２する。\n[誘発] 相手ターン開始時、このキャラが中央ＤＦに登場している場合、味方ＤＦ[花]キャラ全てにＳＰ＋１する。\n[宣言][切札] [0]:自分のゴミ箱の切札効果を持つカードを４枚までデッキの下に置きシャッフルする。",
  "textKr": "[サポーター:[花]]\n[誘発] このキャラが手札から登場したとき、コストが３点以上の味方[花]キャラが３体以上の場合、２枚ドローする。自分にシールド＋２する。\n[誘発] 相手ターン開始時、このキャラが中央ＤＦに登場している場合、味方ＤＦ[花]キャラ全てにＳＰ＋１する。\n[宣言][切札] [0]:自分のゴミ箱の切札効果を持つカードを４枚までデッキの下に置きシャッフルする。",
  "sourceUrl": "https://lycee-tcg.com/card/card_detail.pl?cardno=LO-5644"
}
