{
  "cardNo": "LO-6298",
  "title": "二世勢州千子右衛門尉村正",
  "subName": "銀星号",
  "name": "二世勢州千子右衛門尉村正 銀星号",
  "rawTypeJa": "キャラクター",
  "rawTypeKr": "캐릭터",
  "type": "character",
  "rarity": "R",
  "attributes": [
    "moon"
  ],
  "useTarget": [
    "moon",
    "moon",
    "moon",
    "moon",
    "moon",
    "moon",
    "moon"
  ],
  "ap": 10,
  "dp": 10,
  "sp": 0,
  "dmg": 5,
  "ex": 2,
  "costRaw": "月月月月月月月",
  "restrictionRaw": "",
  "typeTagsRaw": "",
  "text": "[ジャンプ:[0]]\n[常時] 味方キャラ全てにＡＰ＋１・ＤＰ＋１する。\n[宣言] [0]:{相手キャラ１体}にＡＰ－３またはＤＰ－３する。\n[誘発] このキャラが登場したターン中を除く自ターン終了時、またはこのキャラが場を離れたとき、このキャラを破棄する。このキャラのチャージとして置かれていたゴミ箱のキャラのうち１体を、次の相手ターン開始時までＤＭＧを０にし元の効果全てを失い、無償で登場できる。\n[手札宣言] [0]:自分のゴミ箱または自分のデッキから「湊斗光」または「二世村正」１体を探し公開して手札に入れる。",
  "textKr": "[ジャンプ:[0]]\n[常時] 味方キャラ全てにＡＰ＋１・ＤＰ＋１する。\n[宣言] [0]:{相手キャラ１体}にＡＰ－３またはＤＰ－３する。\n[誘発] このキャラが登場したターン中を除く自ターン終了時、またはこのキャラが場を離れたとき、このキャラを破棄する。このキャラのチャージとして置かれていたゴミ箱のキャラのうち１体を、次の相手ターン開始時までＤＭＧを０にし元の効果全てを失い、無償で登場できる。\n[手札宣言] [0]:自分のゴミ箱または自分のデッキから「湊斗光」または「二世村正」１体を探し公開して手札に入れる。",
  "sourceUrl": "https://lycee-tcg.com/card/card_detail.pl?cardno=LO-6298"
}
