{
  "cardNo": "LO-6620",
  "title": "パパ活常連客の教師",
  "subName": "東海林",
  "name": "パパ活常連客の教師 東海林",
  "rawTypeJa": "キャラクター",
  "rawTypeKr": "캐릭터",
  "type": "character",
  "rarity": "C",
  "attributes": [
    "cosmos"
  ],
  "useTarget": [
    "cosmos",
    "cosmos",
    "star"
  ],
  "ap": 1,
  "dp": 6,
  "sp": 2,
  "dmg": 0,
  "ex": 2,
  "costRaw": "宙宙無",
  "restrictionRaw": "",
  "typeTagsRaw": "",
  "text": "[誘発] このキャラが手札から登場したとき、味方アイテムが１枚以上の場合、１枚ドローする。",
  "textKr": "[誘発] このキャラが手札から登場したとき、味方アイテムが１枚以上の場合、１枚ドローする。",
  "sourceUrl": "https://lycee-tcg.com/card/card_detail.pl?cardno=LO-6620"
}
