{
  "cardNo": "LO-6174",
  "title": "放浪する一匹狼",
  "subName": "ヴェオ",
  "name": "放浪する一匹狼 ヴェオ",
  "rawTypeJa": "キャラクター",
  "rawTypeKr": "캐릭터",
  "type": "character",
  "rarity": "U",
  "attributes": [
    "sun"
  ],
  "useTarget": [
    "sun",
    "sun",
    "sun"
  ],
  "ap": 6,
  "dp": 6,
  "sp": 0,
  "dmg": 3,
  "ex": 2,
  "costRaw": "日日日",
  "restrictionRaw": "",
  "typeTagsRaw": "",
  "text": "[ジャンプ:[0]][チャージ:２]\n[常時] このキャラはサポートで能力値修正を得ない。\n[宣言] [C1][日日]:このキャラにＡＰ＋４・ＤＰ＋４する。\n[宣言] [C1][日日]:このキャラを横に置く。このターン終了時、横のこのキャラを元の[チャージ]１つを失い無償で登場できる。",
  "textKr": "[ジャンプ:[0]][チャージ:２]\n[常時] このキャラはサポートで能力値修正を得ない。\n[宣言] [C1][日日]:このキャラにＡＰ＋４・ＤＰ＋４する。\n[宣言] [C1][日日]:このキャラを横に置く。このターン終了時、横のこのキャラを元の[チャージ]１つを失い無償で登場できる。",
  "sourceUrl": "https://lycee-tcg.com/card/card_detail.pl?cardno=LO-6174",
  "parsedEffectsDraft": [
    {
      "header": "宣言",
      "timing": "onUse",
      "originalLine": "[宣言] [C1][日日]:このキャラにAP+4・DP+4する。",
      "actions": [
        {
          "type": "modifyStat",
          "stat": "ap",
          "amount": 4
        }
      ]
    }
  ],
  "parseMeta": {
    "originalText": "[ジャンプ:[0]][チャージ:２]\n[常時] このキャラはサポートで能力値修正を得ない。\n[宣言] [C1][日日]:このキャラにＡＰ＋４・ＤＰ＋４する。\n[宣言] [C1][日日]:このキャラを横に置く。このターン終了時、横のこのキャラを元の[チャージ]１つを失い無償で登場できる。",
    "normalizedText": "[ジャンプ:[0]][チャージ:2]\n[常時] このキャラはサポートで能力値修正を得ない。\n[宣言] [C1][日日]:このキャラにAP+4・DP+4する。\n[宣言] [C1][日日]:このキャラを横に置く。このターン終了時、横のこのキャラを元の[チャージ]1つを失い無償で登場できる。",
    "lines": [
      "[ジャンプ:[0]][チャージ:2]",
      "[常時] このキャラはサポートで能力値修正を得ない。",
      "[宣言] [C1][日日]:このキャラにAP+4・DP+4する。",
      "[宣言] [C1][日日]:このキャラを横に置く。このターン終了時、横のこのキャラを元の[チャージ]1つを失い無償で登場できる。"
    ],
    "matchedRuleIds": [
      "modifyStat"
    ]
  },
  "unresolvedTextLines": [
    {
      "line": "[ジャンプ:[0]][チャージ:2]",
      "reason": "no parser rule matched"
    },
    {
      "line": "[常時] このキャラはサポートで能力値修正を得ない。",
      "reason": "no parser rule matched"
    },
    {
      "line": "[宣言] [C1][日日]:このキャラを横に置く。このターン終了時、横のこのキャラを元の[チャージ]1つを失い無償で登場できる。",
      "reason": "no parser rule matched"
    }
  ]
}
