{
  "cardNo": "LO-6095",
  "title": "シュロ寮男子寮長",
  "subName": "ギドウ",
  "name": "シュロ寮男子寮長 ギドウ",
  "rawTypeJa": "キャラクター",
  "rawTypeKr": "캐릭터",
  "type": "character",
  "rarity": "U",
  "attributes": [
    "snow"
  ],
  "useTarget": [
    "snow",
    "snow",
    "snow"
  ],
  "ap": 5,
  "dp": 5,
  "sp": 2,
  "dmg": 0,
  "ex": 2,
  "costRaw": "雪雪雪",
  "restrictionRaw": "－－－●●●",
  "typeTagsRaw": "",
  "text": "[サイドステップ:[0]][チャージ:２][エンゲージ:[自分にシールド＋１できる。]]\n[誘発] 自分のコストが１点以上の能力・エリアの効果を使用したとき、味方キャラ１体にＡＰ＋１・ＤＰ＋１する。（１ターンに３回まで処理可能）\n[宣言] [C1][雪]:{味方キャラ１体}にＡＰ＋２・ＤＰ＋２する。\n[宣言] [雪雪]:対応・バトル中を除く自ターン中に使用する。自分の「ループ」置き場の枚数が８枚以上の場合、{相手キャラ１体}を破棄する。（ゲーム中１回まで使用可能）\n[手札宣言] [0]:自分のゴミ箱または自分のデッキから「服飾専攻の健気な後輩 サクヤ」１体を探し公開して手札に入れる。\n構築制限:【[CAB]】【[雪]】",
  "textKr": "[サイドステップ:[0]][チャージ:２][エンゲージ:[自分にシールド＋１できる。]]\n[誘発] 自分のコストが１点以上の能力・エリアの効果を使用したとき、味方キャラ１体にＡＰ＋１・ＤＰ＋１する。（１ターンに３回まで処理可能）\n[宣言] [C1][雪]:{味方キャラ１体}にＡＰ＋２・ＤＰ＋２する。\n[宣言] [雪雪]:対応・バトル中を除く自ターン中に使用する。自分の「ループ」置き場の枚数が８枚以上の場合、{相手キャラ１体}を破棄する。（ゲーム中１回まで使用可能）\n[手札宣言] [0]:自分のゴミ箱または自分のデッキから「服飾専攻の健気な後輩 サクヤ」１体を探し公開して手札に入れる。\n構築制限:【[CAB]】【[雪]】",
  "sourceUrl": "https://lycee-tcg.com/card/card_detail.pl?cardno=LO-6095",
  "parsedEffectsDraft": [
    {
      "header": "誘発",
      "timing": "unknown",
      "originalLine": "[誘発] 自分のコストが1点以上の能力・エリアの効果を使用したとき、味方キャラ1体にAP+1・DP+1する。(1ターンに3回まで処理可能)",
      "actions": [
        {
          "type": "modifyStat",
          "stat": "ap",
          "amount": 1
        }
      ]
    },
    {
      "header": "宣言",
      "timing": "onUse",
      "originalLine": "[宣言] [C1][雪]:{味方キャラ1体}にAP+2・DP+2する。",
      "actions": [
        {
          "type": "modifyStat",
          "stat": "ap",
          "amount": 2
        }
      ]
    },
    {
      "header": "手札宣言",
      "timing": "onUse",
      "originalLine": "[手札宣言] [0]:自分のゴミ箱または自分のデッキから「服飾専攻の健気な後輩 サクヤ」1体を探し公開して手札に入れる。",
      "actions": [
        {
          "type": "searchCard",
          "owner": "self",
          "zones": [
            "deck",
            "trash",
            "hand"
          ],
          "match": {
            "exactName": "服飾専攻の健気な後輩 サクヤ"
          },
          "min": 0,
          "max": 0,
          "storeAs": "lastSearchResult",
          "shuffleAfterSearch": true
        }
      ]
    }
  ],
  "parseMeta": {
    "originalText": "[サイドステップ:[0]][チャージ:２][エンゲージ:[自分にシールド＋１できる。]]\n[誘発] 自分のコストが１点以上の能力・エリアの効果を使用したとき、味方キャラ１体にＡＰ＋１・ＤＰ＋１する。（１ターンに３回まで処理可能）\n[宣言] [C1][雪]:{味方キャラ１体}にＡＰ＋２・ＤＰ＋２する。\n[宣言] [雪雪]:対応・バトル中を除く自ターン中に使用する。自分の「ループ」置き場の枚数が８枚以上の場合、{相手キャラ１体}を破棄する。（ゲーム中１回まで使用可能）\n[手札宣言] [0]:自分のゴミ箱または自分のデッキから「服飾専攻の健気な後輩 サクヤ」１体を探し公開して手札に入れる。\n構築制限:【[CAB]】【[雪]】",
    "normalizedText": "[サイドステップ:[0]][チャージ:2][エンゲージ:[自分にシールド+1できる。]]\n[誘発] 自分のコストが1点以上の能力・エリアの効果を使用したとき、味方キャラ1体にAP+1・DP+1する。(1ターンに3回まで処理可能)\n[宣言] [C1][雪]:{味方キャラ1体}にAP+2・DP+2する。\n[宣言] [雪雪]:対応・バトル中を除く自ターン中に使用する。自分の「ループ」置き場の枚数が8枚以上の場合、{相手キャラ1体}を破棄する。(ゲーム中1回まで使用可能)\n[手札宣言] [0]:自分のゴミ箱または自分のデッキから「服飾専攻の健気な後輩 サクヤ」1体を探し公開して手札に入れる。\n構築制限:【[CAB]】【[雪]】",
    "lines": [
      "[サイドステップ:[0]][チャージ:2][エンゲージ:[自分にシールド+1できる。]]",
      "[誘発] 自分のコストが1点以上の能力・エリアの効果を使用したとき、味方キャラ1体にAP+1・DP+1する。(1ターンに3回まで処理可能)",
      "[宣言] [C1][雪]:{味方キャラ1体}にAP+2・DP+2する。",
      "[宣言] [雪雪]:対応・バトル中を除く自ターン中に使用する。自分の「ループ」置き場の枚数が8枚以上の場合、{相手キャラ1体}を破棄する。(ゲーム中1回まで使用可能)",
      "[手札宣言] [0]:自分のゴミ箱または自分のデッキから「服飾専攻の健気な後輩 サクヤ」1体を探し公開して手札に入れる。",
      "構築制限:【[CAB]】【[雪]】"
    ],
    "matchedRuleIds": [
      "modifyStat",
      "modifyStat",
      "searchCard"
    ]
  },
  "unresolvedTextLines": [
    {
      "line": "[サイドステップ:[0]][チャージ:2][エンゲージ:[自分にシールド+1できる。]]",
      "reason": "no parser rule matched"
    },
    {
      "line": "[宣言] [雪雪]:対応・バトル中を除く自ターン中に使用する。自分の「ループ」置き場の枚数が8枚以上の場合、{相手キャラ1体}を破棄する。(ゲーム中1回まで使用可能)",
      "reason": "no parser rule matched"
    },
    {
      "line": "構築制限:【[CAB]】【[雪]】",
      "reason": "no parser rule matched"
    }
  ]
}
